atmos-ld
setup.cfg
setup.py
atmos_ld/__init__.py
atmos_ld/atmosphere.ttl
atmos_ld/eco.py
atmos_ld/metadata.json
atmos_ld/ted.ttl
atmos_ld.egg-info/PKG-INFO
atmos_ld.egg-info/SOURCES.txt
atmos_ld.egg-info/dependency_links.txt
atmos_ld.egg-info/requires.txt
atmos_ld.egg-info/top_level.txt